rci/Client.py
rci/Exceptions.py
rci/__init__.py
rci_py_client-1.0.4.dist-info/METADATA
rci_py_client-1.0.4.dist-info/WHEEL
rci_py_client-1.0.4.dist-info/top_level.txt
rci_py_client-1.0.4.dist-info/RECORD
