Metadata-Version: 2.1
Name: rci-py-client
Version: 1.0.4
Summary: RCI Python client
Home-page: https://github.com/Jakub21
Author: Jakub21
Author-email: UNKNOWN
License: MIT
Platform: UNKNOWN
